umlsrat/__init__.py
umlsrat/api/__init__.py
umlsrat/api/metathesaurus.py
umlsrat/api/rat_session.py
umlsrat/const.py
umlsrat/lookup/__init__.py
umlsrat/lookup/graph_fn.py
umlsrat/lookup/lookup_defs.py
umlsrat/lookup/lookup_desc.py
umlsrat/lookup/lookup_umls.py
umlsrat/util/__init__.py
umlsrat/util/args_util.py
umlsrat/util/cui_order.py
umlsrat/util/iterators.py
umlsrat/util/orderedset.py
umlsrat/util/text.py
umls_rat-0.6.8.dist-info/LICENSE
umls_rat-0.6.8.dist-info/METADATA
umls_rat-0.6.8.dist-info/WHEEL
umls_rat-0.6.8.dist-info/RECORD
