Metadata-Version: 2.1
Name: umls-rat
Version: 0.6.8
Summary: UMLS RAT (REST API Tool) provides a reasonable interface to the UMLS MetaThesaurus via the REST API.
Home-page: https://github.com/3mcloud/umls-rat
License: MIT
Keywords: umls
Author: Russell Klopfer
Author-email: rklopfer@mmm.com
Requires-Python: >=3.8,<4.0
Classifier: License :: OSI Approved :: MIT License
Classifier: Programming Language :: Python :: 3
Classifier: Programming Language :: Python :: 3.8
Classifier: Programming Language :: Python :: 3.9
Classifier: Programming Language :: Python :: 3.10
Classifier: Programming Language :: Python :: 3.11
Classifier: Programming Language :: Python :: 3.12
Requires-Dist: backoff (>=2.2.1,<3.0.0)
Requires-Dist: ratelimit (>=2.2.1,<3.0.0)
Requires-Dist: requests (>=2.31.0,<3.0.0)
Requires-Dist: requests-cache (>=1.1.0,<2.0.0)
Requires-Dist: urllib3 (>=2.0.5,<3.0.0)
Project-URL: Documentation, https://urls-rat.readthedocs.io
Project-URL: Repository, https://github.com/3mcloud/umls-rat
